rwa/__init__.py
rwa/rwaPython.cpython-310-x86_64-linux-gnu.so
rwa-1.0.0.2.dist-info/METADATA
rwa-1.0.0.2.dist-info/WHEEL
rwa-1.0.0.2.dist-info/RECORD
